bcqa/__init__.py
bcqa/config/__init__.py
bcqa/config/constants.py
bcqa/data/__init__.py
bcqa/data/datastructures/AnnConstants.py
bcqa/data/datastructures/LLmConstants.py
bcqa/data/datastructures/__init__.py
bcqa/data/datastructures/answer.py
bcqa/data/datastructures/dataset.py
bcqa/data/datastructures/evidence.py
bcqa/data/datastructures/question.py
bcqa/data/datastructures/sample.py
bcqa/data/datastructures/hyperparameters/__init__.py
bcqa/data/datastructures/hyperparameters/base.py
bcqa/data/datastructures/hyperparameters/dpr.py
bcqa/data/datastructures/hyperparameters/tapas.py
bcqa/data/loaders/AmbigQADataLoader.py
bcqa/data/loaders/BaseDataLoader.py
bcqa/data/loaders/DataLoaderFactory.py
bcqa/data/loaders/DprDataLoader.py
bcqa/data/loaders/FinQADataLoader.py
bcqa/data/loaders/HfDataLoader.py
bcqa/data/loaders/MusiqueQaDataLoader.py
bcqa/data/loaders/OTTQADataLoader.py
bcqa/data/loaders/ReaderDataLoader.py
bcqa/data/loaders/RetrieverDataset.py
bcqa/data/loaders/StrategyQADataLoader.py
bcqa/data/loaders/TATQADataLoader.py
bcqa/data/loaders/Tokenizer.py
bcqa/data/loaders/WikiMultihopQADataLoader.py
bcqa/data/loaders/__init__.py
bcqa/evaluation/__init__.py
bcqa/losses/BaseLoss.py
bcqa/losses/DprNllLoss.py
bcqa/losses/__init__.py
bcqa/methods/__init__.py
bcqa/methods/utils.py
bcqa/methods/ir/__init__.py
bcqa/methods/ir/dense/__init__.py
bcqa/methods/ir/dense/dpr/__init__.py
bcqa/methods/ir/dense/dpr/indexer/__init__.py
bcqa/methods/ir/dense/dpr/indexer/annoyIndexer.py
bcqa/methods/ir/dense/dpr/indexer/faissIndexer.py
bcqa/methods/ir/dense/dpr/indexer/indexer.py
bcqa/methods/ir/dense/dpr/models/__init__.py
bcqa/methods/ir/dense/dpr/models/bi_encoder.py
bcqa/methods/ir/dense/dpr/models/dpr_sentence_transformers_inference.py
bcqa/methods/llms/__init__.py
bcqa/methods/llms/flant5_engine.py
bcqa/methods/llms/llama_engine.py
bcqa/methods/llms/llm_engine_orchestrator.py
bcqa/methods/llms/openai_engine.py
bcqa/metrics/ExactMatch.py
bcqa/metrics/MetricsBase.py
bcqa-1.1.4.dist-info/METADATA
bcqa-1.1.4.dist-info/WHEEL
bcqa-1.1.4.dist-info/top_level.txt
bcqa-1.1.4.dist-info/RECORD
